followthemoney/__init__.py
followthemoney/compare.py
followthemoney/entity.py
followthemoney/exc.py
followthemoney/graph.py
followthemoney/helpers.py
followthemoney/messages.py
followthemoney/model.py
followthemoney/names.py
followthemoney/namespace.py
followthemoney/ontology.py
followthemoney/property.py
followthemoney/proxy.py
followthemoney/py.typed
followthemoney/schema.py
followthemoney/settings.py
followthemoney/util.py
followthemoney/value.py
followthemoney/cli/__init__.py
followthemoney/cli/aggregate.py
followthemoney/cli/cli.py
followthemoney/cli/exports.py
followthemoney/cli/mapping.py
followthemoney/cli/sieve.py
followthemoney/cli/statement.py
followthemoney/cli/util.py
followthemoney/dataset/__init__.py
followthemoney/dataset/catalog.py
followthemoney/dataset/coverage.py
followthemoney/dataset/dataset.py
followthemoney/dataset/publisher.py
followthemoney/dataset/resource.py
followthemoney/dataset/util.py
followthemoney/export/__init__.py
followthemoney/export/common.py
followthemoney/export/csv.py
followthemoney/export/excel.py
followthemoney/export/graph.py
followthemoney/export/neo4j.py
followthemoney/export/rdf.py
followthemoney/mapping/__init__.py
followthemoney/mapping/csv.py
followthemoney/mapping/entity.py
followthemoney/mapping/property.py
followthemoney/mapping/query.py
followthemoney/mapping/source.py
followthemoney/mapping/sql.py
followthemoney/schema/Address.yaml
followthemoney/schema/Airplane.yaml
followthemoney/schema/Analyzable.yaml
followthemoney/schema/Article.yaml
followthemoney/schema/Asset.yaml
followthemoney/schema/Associate.yaml
followthemoney/schema/Audio.yaml
followthemoney/schema/BankAccount.yaml
followthemoney/schema/Call.yaml
followthemoney/schema/CallForTenders.yaml
followthemoney/schema/Company.yaml
followthemoney/schema/Contract.yaml
followthemoney/schema/ContractAward.yaml
followthemoney/schema/CourtCase.yaml
followthemoney/schema/CourtCaseParty.yaml
followthemoney/schema/CryptoWallet.yaml
followthemoney/schema/Debt.yaml
followthemoney-4.5.0.dist-info/METADATA
followthemoney-4.5.0.dist-info/WHEEL
followthemoney-4.5.0.dist-info/entry_points.txt
followthemoney-4.5.0.dist-info/licenses/LICENSE
followthemoney-4.5.0.dist-info/RECORD
