Metadata-Version: 2.4
Name: followthemoney
Version: 4.5.0
Summary: A data model for anti corruption data modeling and analysis.
Project-URL: Documentation, https://followthemoney.tech/
Project-URL: Repository, https://github.com/opensanctions/followthemoney.git
Project-URL: Issues, https://github.com/opensanctions/followthemoney/issues
Author-email: OpenSanctions <info@opensanctions.org>, DARC <hi@dataresearchcenter.org>
License: MIT License
License-File: LICENSE
Classifier: Intended Audience :: Developers
Classifier: License :: OSI Approved :: MIT License
Classifier: Operating System :: OS Independent
Classifier: Programming Language :: Python :: 3.10
Classifier: Programming Language :: Python :: 3.11
Classifier: Programming Language :: Python :: 3.12
Requires-Python: >=3.10
Requires-Dist: babel<3.0.0,>=2.14.0
Requires-Dist: banal<1.1.0,>=1.0.6
Requires-Dist: click<9.0.0,>=8.0
Requires-Dist: networkx<3.5,>=2.5
Requires-Dist: normality<4.0.0,>=3.0.1
Requires-Dist: openpyxl<4.0.0,>=3.0.5
Requires-Dist: orjson<4.0,>=3.10.0
Requires-Dist: phonenumbers<10.0.0,>=8.12.22
Requires-Dist: prefixdate<1.0.0,>=0.5.0
Requires-Dist: pydantic<3.0.0,>=2.11.0
Requires-Dist: pytz>=2021.1
Requires-Dist: pyyaml<7.0.0,>=5.0.0
Requires-Dist: rdflib<7.6.0,>=6.2.0
Requires-Dist: requests<3.0.0,>=2.21.0
Requires-Dist: rigour<2.0.0,>=1.6.0
Requires-Dist: sqlalchemy[mypy]<3.0.0,>=2.0.0
Provides-Extra: dev
Requires-Dist: build; extra == 'dev'
Requires-Dist: bump2version; extra == 'dev'
Requires-Dist: coverage>=4.1; extra == 'dev'
Requires-Dist: flake8>=2.6.0; extra == 'dev'
Requires-Dist: mypy; extra == 'dev'
Requires-Dist: pip>=10.0.0; extra == 'dev'
Requires-Dist: pytest; extra == 'dev'
Requires-Dist: pytest-cov; extra == 'dev'
Requires-Dist: recommonmark>=0.4.0; extra == 'dev'
Requires-Dist: responses>=0.9.0; extra == 'dev'
Requires-Dist: transifex-client; extra == 'dev'
Requires-Dist: twine; extra == 'dev'
Requires-Dist: types-openpyxl; extra == 'dev'
Requires-Dist: types-pyyaml; extra == 'dev'
Requires-Dist: types-requests; extra == 'dev'
Requires-Dist: types-setuptools; extra == 'dev'
Requires-Dist: wheel>=0.29.0; extra == 'dev'
Provides-Extra: docs
Requires-Dist: mkdocs-gen-files; extra == 'docs'
Requires-Dist: mkdocs-macros-plugin; extra == 'docs'
Requires-Dist: mkdocs-material>=9.0.0; extra == 'docs'
Requires-Dist: mkdocs>=1.4.0; extra == 'docs'
Requires-Dist: mkdocstrings[python]; extra == 'docs'
